parsomics/__init__.py
parsomics-0.2.2.dist-info/METADATA
parsomics-0.2.2.dist-info/WHEEL
parsomics-0.2.2.dist-info/RECORD
